unitunes/__init__.py
unitunes/file_manager.py
unitunes/gui/engine.py
unitunes/gui/main.py
unitunes/index.py
unitunes/main.py
unitunes/matcher.py
unitunes/playlist.py
unitunes/pull_playlist.py
unitunes/searcher.py
unitunes/services/beatsaber.py
unitunes/services/musicbrainz.py
unitunes/services/services.py
unitunes/services/spotify.py
unitunes/services/ytm.py
unitunes/track.py
unitunes/types.py
unitunes/uri.py
unitunes-2.0.1.dist-info/entry_points.txt
unitunes-2.0.1.dist-info/LICENSE.txt
unitunes-2.0.1.dist-info/WHEEL
unitunes-2.0.1.dist-info/METADATA
unitunes-2.0.1.dist-info/RECORD
