Metadata-Version: 2.1
Name: unitunes
Version: 2.0.1
Summary: A GUI and library to manage playlists across music streaming services.
Home-page: https://github.com/platers/unitunes
License: GPLv3
Keywords: gui,music,playlist,playlists,spotify,ytmusic,musicbrainz
Author: platers
Author-email: platers81@gmail.com
Requires-Python: >=3.9,<4.0
Classifier: Development Status :: 3 - Alpha
Classifier: Intended Audience :: End Users/Desktop
Classifier: License :: OSI Approved :: GNU General Public License v3 (GPLv3)
Classifier: License :: Other/Proprietary License
Classifier: Natural Language :: English
Classifier: Programming Language :: Python :: 3
Classifier: Programming Language :: Python :: 3.10
Classifier: Programming Language :: Python :: 3.9
Classifier: Topic :: Utilities
Requires-Dist: appdirs (>=1.4.4,<2.0.0)
Requires-Dist: dearpygui (>=1.6.2,<2.0.0)
Requires-Dist: musicbrainzngs (>=0.7.1,<0.8.0)
Requires-Dist: pydantic (>=1.9.0,<2.0.0)
Requires-Dist: ratelimit (>=2.2.1,<3.0.0)
Requires-Dist: spotipy (>=2.19.0,<3.0.0)
Requires-Dist: strsimpy (>=0.2.1,<0.3.0)
Requires-Dist: tqdm (>=4.64.0,<5.0.0)
Requires-Dist: youtube-title-parse (>=1.0.0,<2.0.0)
Requires-Dist: ytmusicapi (>=0.21.0,<0.22.0)
